shaded/__init__.py
shaded/band_projection_matrix.py
shaded/chained_spectral_projector.py
shaded/linalg_utils.py
shaded/pair_wise_lda.py
shaded/pseudo_lda.py
shaded/pseudo_pca.py
shaded/util.py
shaded/tests/__init__.py
shaded/tests/test_chained_spectral_projection.py
shaded/tests/test_linalg_utils.py
shaded-0.1.5.dist-info/LICENSE
shaded-0.1.5.dist-info/METADATA
shaded-0.1.5.dist-info/WHEEL
shaded-0.1.5.dist-info/top_level.txt
shaded-0.1.5.dist-info/RECORD
