Metadata-Version: 2.1
Name: shaded
Version: 0.1.5
Summary: Tools for linear dimension reduction
Home-page: https://github.com/i2mint/shaded
License: apache-2.0
Platform: any
License-File: LICENSE
Requires-Dist: importlib-resources
Requires-Dist: matplotlib
Requires-Dist: numpy
Requires-Dist: oplot
Requires-Dist: pytest
Requires-Dist: scikit-learn
